pyprop8/__init__.py
pyprop8/_core.py
pyprop8/_propagators.py
pyprop8/_scaledmatrix.py
pyprop8/tests.py
pyprop8/utils.py
pyprop8-1.1.5.dist-info/LICENSE
pyprop8-1.1.5.dist-info/METADATA
pyprop8-1.1.5.dist-info/WHEEL
pyprop8-1.1.5.dist-info/top_level.txt
pyprop8-1.1.5.dist-info/RECORD
