Metadata-Version: 2.1
Name: pyprop8
Version: 1.1.5
Summary: A lightweight package for synthetic seismograms
Home-page: https://github.com/valentineap/pyprop8
Author: Andrew Valentine
Author-email: andrew.valentine@durham.ac.uk
Project-URL: Bug Tracker, https://github.com/valentineap/pyprop8/issues
Classifier: Programming Language :: Python :: 3
Classifier: License :: OSI Approved :: GNU General Public License v3 (GPLv3)
Classifier: Operating System :: OS Independent
Requires-Python: >=3.6
License-File: LICENSE
Requires-Dist: numpy
Requires-Dist: scipy
